{
    "XamlType": "Microsoft.ReactNative.ViewPanel",
    "Background": "null",
    "BorderBrush": "#00000000",
    "BorderThickness": "0,0,0,0",
    "Clip": "null",
    "CornerRadius": "0,0,0,0",
    "FlowDirection": "LeftToRight",
    "Height": "360",
    "HorizontalAlignment": "Stretch",
    "Margin": "0,0,0,0",
    "RenderSize": "800,360",
    "VerticalAlignment": "Stretch",
    "Visibility": "Visible",
    "Width": "800",
    "children": [
    {
        "XamlType": "Windows.UI.Xaml.Controls.ToggleSwitch",
        "Background": "#33E1E1E1",
        "BorderBrush": "#55FF00FF",
        "BorderThickness": "1,1,1,1",
        "Clip": "null",
        "CornerRadius": "0,0,0,0",
        "FlowDirection": "LeftToRight",
        "Foreground": "#FFFFFFFF",
        "Height": "50",
        "HorizontalAlignment": "Left",
        "Margin": "0,0,0,0",
        "Padding": "0,0,0,0",
        "RenderSize": "50.85714,50.28571",
        "VerticalAlignment": "Center",
        "Visibility": "Visible",
        "Width": "51",
        "children": [
        {
            "XamlType": "Windows.UI.Xaml.Controls.Grid",
            "Background": "#33E1E1E1",
            "BorderBrush": "#55FF00FF",
            "BorderThickness": "1,1,1,1",
            "Clip": "null",
            "CornerRadius": "0,0,0,0",
            "FlowDirection": "LeftToRight",
            "HorizontalAlignment": "Stretch",
            "Margin": "0,0,0,0",
            "Padding": "0,0,0,0",
            "RenderSize": "50.85714,50.28571",
            "VerticalAlignment": "Stretch",
            "Visibility": "Visible",
            "children": [
            {
                "XamlType": "Windows.UI.Xaml.Controls.Grid",
                "Background": "null",
                "BorderBrush": "null",
                "BorderThickness": "0,0,0,0",
                "Clip": "null",
                "CornerRadius": "0,0,0,0",
                "FlowDirection": "LeftToRight",
                "HorizontalAlignment": "Left",
                "Margin": "0,0,0,0",
                "Padding": "0,0,0,0",
                "RenderSize": "154.2857,32.57143",
                "VerticalAlignment": "Top",
                "Visibility": "Visible",
                "children": [
                {
                    "XamlType": "Windows.UI.Xaml.Controls.Grid",
                    "Background": "#00FFFFFF",
                    "BorderBrush": "null",
                    "BorderThickness": "0,0,0,0",
                    "Clip": "null",
                    "CornerRadius": "0,0,0,0",
                    "FlowDirection": "LeftToRight",
                    "HorizontalAlignment": "Stretch",
                    "Margin": "0,5,0,5",
                    "Name": "SwitchAreaGrid",
                    "Padding": "0,0,0,0",
                    "RenderSize": "52,22.85714",
                    "VerticalAlignment": "Stretch",
                    "Visibility": "Visible"
                },
                {
                    "XamlType": "Windows.UI.Xaml.Controls.ContentPresenter",
                    "Background": "null",
                    "BorderBrush": "null",
                    "BorderThickness": "0,0,0,0",
                    "Clip": "null",
                    "CornerRadius": "0,0,0,0",
                    "FlowDirection": "LeftToRight",
                    "Foreground": "#FFFFFFFF",
                    "HorizontalAlignment": "Left",
                    "Margin": "0,0,0,0",
                    "Name": "OffContentPresenter",
                    "Padding": "0,0,0,0",
                    "RenderSize": "0,0",
                    "VerticalAlignment": "Center",
                    "Visibility": "Visible"
                },
                {
                    "XamlType": "Windows.UI.Xaml.Controls.ContentPresenter",
                    "Background": "null",
                    "BorderBrush": "null",
                    "BorderThickness": "0,0,0,0",
                    "Clip": "null",
                    "CornerRadius": "0,0,0,0",
                    "FlowDirection": "LeftToRight",
                    "Foreground": "#FFFFFFFF",
                    "HorizontalAlignment": "Left",
                    "Margin": "0,0,0,0",
                    "Name": "OnContentPresenter",
                    "Padding": "0,0,0,0",
                    "RenderSize": "0,0",
                    "VerticalAlignment": "Center",
                    "Visibility": "Visible"
                },
                {
                    "XamlType": "Windows.UI.Xaml.Shapes.Rectangle",
                    "Clip": "null",
                    "FlowDirection": "LeftToRight",
                    "Height": "20",
                    "HorizontalAlignment": "Stretch",
                    "Margin": "0,0,0,0",
                    "Name": "OuterBorder",
                    "RenderSize": "40,20",
                    "VerticalAlignment": "Stretch",
                    "Visibility": "Visible",
                    "Width": "40"
                },
                {
                    "XamlType": "Windows.UI.Xaml.Shapes.Rectangle",
                    "Clip": "null",
                    "FlowDirection": "LeftToRight",
                    "Height": "20",
                    "HorizontalAlignment": "Stretch",
                    "Margin": "0,0,0,0",
                    "Name": "SwitchKnobBounds",
                    "RenderSize": "40,20",
                    "VerticalAlignment": "Stretch",
                    "Visibility": "Visible",
                    "Width": "40"
                },
                {
                    "XamlType": "Windows.UI.Xaml.Controls.Grid",
                    "Background": "null",
                    "BorderBrush": "null",
                    "BorderThickness": "0,0,0,0",
                    "Clip": "null",
                    "CornerRadius": "0,0,0,0",
                    "FlowDirection": "LeftToRight",
                    "Height": "20",
                    "HorizontalAlignment": "Left",
                    "Margin": "0,0,0,0",
                    "Name": "SwitchKnob",
                    "Padding": "0,0,0,0",
                    "RenderSize": "20,20",
                    "VerticalAlignment": "Stretch",
                    "Visibility": "Visible",
                    "Width": "20",
                    "children": [
                    {
                        "XamlType": "Windows.UI.Xaml.Shapes.Ellipse",
                        "Clip": "null",
                        "FlowDirection": "LeftToRight",
                        "Height": "10",
                        "HorizontalAlignment": "Stretch",
                        "Margin": "0,0,0,0",
                        "Name": "SwitchKnobOn",
                        "RenderSize": "10.28571,10.28571",
                        "VerticalAlignment": "Stretch",
                        "Visibility": "Visible",
                        "Width": "10"
                    },
                    {
                        "XamlType": "Windows.UI.Xaml.Shapes.Ellipse",
                        "Clip": "null",
                        "FlowDirection": "LeftToRight",
                        "Height": "10",
                        "HorizontalAlignment": "Stretch",
                        "Margin": "0,0,0,0",
                        "Name": "SwitchKnobOff",
                        "RenderSize": "10.28571,10.28571",
                        "VerticalAlignment": "Stretch",
                        "Visibility": "Visible",
                        "Width": "10"
                    }
                    ]
                },
                {
                    "XamlType": "Windows.UI.Xaml.Controls.Primitives.Thumb",
                    "Background": "#33000000",
                    "BorderBrush": "#00FFFFFF",
                    "BorderThickness": "1,1,1,1",
                    "Clip": "null",
                    "CornerRadius": "0,0,0,0",
                    "FlowDirection": "LeftToRight",
                    "Foreground": "#FFFFFFFF",
                    "HorizontalAlignment": "Stretch",
                    "Margin": "0,0,0,0",
                    "Name": "SwitchThumb",
                    "Padding": "0,0,0,0",
                    "RenderSize": "52,32.57143",
                    "VerticalAlignment": "Stretch",
                    "Visibility": "Visible",
                    "children": [
                    {
                        "XamlType": "Windows.UI.Xaml.Shapes.Rectangle",
                        "Clip": "null",
                        "FlowDirection": "LeftToRight",
                        "HorizontalAlignment": "Stretch",
                        "Margin": "0,0,0,0",
                        "RenderSize": "52,32.57143",
                        "VerticalAlignment": "Stretch",
                        "Visibility": "Visible"
                    }
                    ]
                }
                ]
            }
            ]
        }
        ]
    },
    {
        "XamlType": "Windows.UI.Xaml.Controls.CheckBox",
        "Background": "#33E1E1E1",
        "BorderBrush": "#55FF00FF",
        "BorderThickness": "1,1,1,1",
        "Clip": "null",
        "CornerRadius": "0,0,0,0",
        "FlowDirection": "LeftToRight",
        "Foreground": "#FFFFFFFF",
        "Height": "50",
        "HorizontalAlignment": "Left",
        "Margin": "0,0,0,0",
        "Padding": "8,5,0,0",
        "RenderSize": "120,50.28571",
        "VerticalAlignment": "Center",
        "Visibility": "Visible",
        "Width": "32",
        "children": [
        {
            "XamlType": "Windows.UI.Xaml.Controls.Grid",
            "Background": "#33E1E1E1",
            "BorderBrush": "#55FF00FF",
            "BorderThickness": "1,1,1,1",
            "Clip": "null",
            "CornerRadius": "0,0,0,0",
            "FlowDirection": "LeftToRight",
            "HorizontalAlignment": "Stretch",
            "Margin": "0,0,0,0",
            "Name": "RootGrid",
            "Padding": "0,0,0,0",
            "RenderSize": "120,50.28571",
            "VerticalAlignment": "Stretch",
            "Visibility": "Visible",
            "children": [
            {
                "XamlType": "Windows.UI.Xaml.Controls.Grid",
                "Background": "null",
                "BorderBrush": "null",
                "BorderThickness": "0,0,0,0",
                "Clip": "null",
                "CornerRadius": "0,0,0,0",
                "FlowDirection": "LeftToRight",
                "Height": "32",
                "HorizontalAlignment": "Stretch",
                "Margin": "0,0,0,0",
                "Padding": "0,0,0,0",
                "RenderSize": "20,32",
                "VerticalAlignment": "Top",
                "Visibility": "Visible",
                "children": [
                {
                    "XamlType": "Windows.UI.Xaml.Shapes.Rectangle",
                    "Clip": "null",
                    "FlowDirection": "LeftToRight",
                    "Height": "20",
                    "HorizontalAlignment": "Stretch",
                    "Margin": "0,0,0,0",
                    "Name": "NormalRectangle",
                    "RenderSize": "20,20",
                    "VerticalAlignment": "Stretch",
                    "Visibility": "Visible",
                    "Width": "20"
                },
                {
                    "XamlType": "Windows.UI.Xaml.Controls.FontIcon",
                    "Clip": "null",
                    "FlowDirection": "LeftToRight",
                    "Foreground": "#FFFFFFFF",
                    "HorizontalAlignment": "Stretch",
                    "Margin": "0,0,0,0",
                    "Name": "CheckGlyph",
                    "RenderSize": "20,32",
                    "VerticalAlignment": "Stretch",
                    "Visibility": "Visible",
                    "children": [
                    {
                        "XamlType": "Windows.UI.Xaml.Controls.Grid",
                        "Background": "#00000000",
                        "BorderBrush": "null",
                        "BorderThickness": "0,0,0,0",
                        "Clip": "null",
                        "CornerRadius": "0,0,0,0",
                        "FlowDirection": "LeftToRight",
                        "HorizontalAlignment": "Stretch",
                        "Margin": "0,0,0,0",
                        "Padding": "0,0,0,0",
                        "RenderSize": "20,32",
                        "VerticalAlignment": "Stretch",
                        "Visibility": "Visible",
                        "children": [
                        {
                            "XamlType": "Windows.UI.Xaml.Controls.TextBlock",
                            "Clip": "null",
                            "FlowDirection": "LeftToRight",
                            "Foreground": "#FFFFFFFF",
                            "HorizontalAlignment": "Stretch",
                            "Margin": "0,0,0,0",
                            "Padding": "0,0,0,0",
                            "RenderSize": "20,16",
                            "VerticalAlignment": "Center",
                            "Visibility": "Visible"
                        }
                        ]
                    }
                    ]
                }
                ]
            },
            {
                "XamlType": "Windows.UI.Xaml.Controls.ContentPresenter",
                "Background": "null",
                "BorderBrush": "null",
                "BorderThickness": "0,0,0,0",
                "Clip": "null",
                "CornerRadius": "0,0,0,0",
                "FlowDirection": "LeftToRight",
                "Foreground": "#FF000000",
                "HorizontalAlignment": "Left",
                "Margin": "8,5,0,0",
                "Name": "ContentPresenter",
                "Padding": "0,0,0,0",
                "RenderSize": "0,0",
                "VerticalAlignment": "Top",
                "Visibility": "Visible"
            }
            ]
        }
        ]
    },
    {
        "XamlType": "Windows.UI.Xaml.Controls.TextBox",
        "Background": "#33E1E1E1",
        "BorderBrush": "#55FF00FF",
        "BorderThickness": "1,1,1,1",
        "Clip": "null",
        "CornerRadius": "0,0,0,0",
        "FlowDirection": "LeftToRight",
        "Foreground": "#FFFFFFFF",
        "Height": "50",
        "HorizontalAlignment": "Stretch",
        "Margin": "0,0,0,0",
        "Padding": "10,10,10,10",
        "RenderSize": "800,50.28571",
        "VerticalAlignment": "Stretch",
        "Visibility": "Visible",
        "Width": "800",
        "children": [
        {
            "XamlType": "Windows.UI.Xaml.Controls.Grid",
            "Background": "null",
            "BorderBrush": "null",
            "BorderThickness": "0,0,0,0",
            "Clip": "null",
            "CornerRadius": "0,0,0,0",
            "FlowDirection": "LeftToRight",
            "HorizontalAlignment": "Stretch",
            "Margin": "0,0,0,0",
            "Padding": "0,0,0,0",
            "RenderSize": "800,50.28571",
            "VerticalAlignment": "Stretch",
            "Visibility": "Visible",
            "children": [
            {
                "XamlType": "Windows.UI.Xaml.Controls.Border",
                "Background": "#33E1E1E1",
                "BorderBrush": "#55FF00FF",
                "BorderThickness": "1,1,1,1",
                "Clip": "null",
                "CornerRadius": "0,0,0,0",
                "FlowDirection": "LeftToRight",
                "HorizontalAlignment": "Stretch",
                "Margin": "0,0,0,0",
                "Name": "BorderElement",
                "Padding": "0,0,0,0",
                "RenderSize": "800,50.28571",
                "VerticalAlignment": "Stretch",
                "Visibility": "Visible"
            },
            {
                "XamlType": "Windows.UI.Xaml.Controls.ScrollViewer",
                "Background": "#00FFFFFF",
                "BorderBrush": "#00FFFFFF",
                "BorderThickness": "0,0,0,0",
                "Clip": "null",
                "CornerRadius": "0,0,0,0",
                "FlowDirection": "LeftToRight",
                "Foreground": "#FFFFFFFF",
                "HorizontalAlignment": "Stretch",
                "Margin": "1,1,1,1",
                "Name": "ContentElement",
                "Padding": "10,10,10,10",
                "RenderSize": "798.2857,48",
                "VerticalAlignment": "Stretch",
                "Visibility": "Visible",
                "children": [
                {
                    "XamlType": "Windows.UI.Xaml.Controls.Border",
                    "Background": "null",
                    "BorderBrush": "#00FFFFFF",
                    "BorderThickness": "0,0,0,0",
                    "Clip": "null",
                    "CornerRadius": "0,0,0,0",
                    "FlowDirection": "LeftToRight",
                    "HorizontalAlignment": "Stretch",
                    "Margin": "0,0,0,0",
                    "Name": "Root",
                    "Padding": "0,0,0,0",
                    "RenderSize": "798.2857,48",
                    "VerticalAlignment": "Stretch",
                    "Visibility": "Visible",
                    "children": [
                    {
                        "XamlType": "Windows.UI.Xaml.Controls.Grid",
                        "Background": "#00FFFFFF",
                        "BorderBrush": "null",
                        "BorderThickness": "0,0,0,0",
                        "Clip": "null",
                        "CornerRadius": "0,0,0,0",
                        "FlowDirection": "LeftToRight",
                        "HorizontalAlignment": "Stretch",
                        "Margin": "0,0,0,0",
                        "Padding": "0,0,0,0",
                        "RenderSize": "798.2857,48",
                        "VerticalAlignment": "Stretch",
                        "Visibility": "Visible",
                        "children": [
                        {
                            "XamlType": "Windows.UI.Xaml.Controls.ScrollContentPresenter",
                            "Background": "null",
                            "BorderBrush": "null",
                            "BorderThickness": "0,0,0,0",
                            "Clip": "Windows.UI.Xaml.Media.RectangleGeometry",
                            "CornerRadius": "0,0,0,0",
                            "FlowDirection": "LeftToRight",
                            "Foreground": "#FFFFFFFF",
                            "HorizontalAlignment": "Stretch",
                            "Margin": "10,10,10,10",
                            "Name": "ScrollContentPresenter",
                            "Padding": "0,0,0,0",
                            "RenderSize": "778.2857,28",
                            "VerticalAlignment": "Stretch",
                            "Visibility": "Visible",
                            "children": [
                            {
                                "XamlType": "Windows.UI.Xaml.FrameworkElement",
                                "Clip": "null",
                                "FlowDirection": "LeftToRight",
                                "HorizontalAlignment": "Stretch",
                                "Margin": "0,0,0,0",
                                "RenderSize": "778.2857,28",
                                "VerticalAlignment": "Stretch",
                                "Visibility": "Visible"
                            }
                            ]
                        },
                        {
                            "XamlType": "Windows.UI.Xaml.Controls.Grid",
                            "Background": "null",
                            "BorderBrush": "null",
                            "BorderThickness": "0,0,0,0",
                            "Clip": "null",
                            "CornerRadius": "0,0,0,0",
                            "FlowDirection": "LeftToRight",
                            "HorizontalAlignment": "Stretch",
                            "Margin": "0,0,0,0",
                            "Padding": "0,0,0,0",
                            "RenderSize": "798.2857,48",
                            "VerticalAlignment": "Stretch",
                            "Visibility": "Visible"
                        },
                        {
                            "XamlType": "Windows.UI.Xaml.Controls.Primitives.ScrollBar",
                            "Background": "#00FFFFFF",
                            "BorderBrush": "#00FFFFFF",
                            "BorderThickness": "0,0,0,0",
                            "Clip": "null",
                            "CornerRadius": "2,2,2,2",
                            "FlowDirection": "LeftToRight",
                            "Foreground": "#00FFFFFF",
                            "HorizontalAlignment": "Right",
                            "Margin": "0,0,0,0",
                            "Name": "VerticalScrollBar",
                            "Padding": "0,0,0,0",
                            "RenderSize": "0,0",
                            "VerticalAlignment": "Stretch",
                            "Visibility": "Collapsed"
                        },
                        {
                            "XamlType": "Windows.UI.Xaml.Controls.Primitives.ScrollBar",
                            "Background": "#00FFFFFF",
                            "BorderBrush": "#00FFFFFF",
                            "BorderThickness": "0,0,0,0",
                            "Clip": "null",
                            "CornerRadius": "2,2,2,2",
                            "FlowDirection": "LeftToRight",
                            "Foreground": "#00FFFFFF",
                            "HorizontalAlignment": "Stretch",
                            "Margin": "0,0,0,0",
                            "Name": "HorizontalScrollBar",
                            "Padding": "0,0,0,0",
                            "RenderSize": "0,0",
                            "VerticalAlignment": "Stretch",
                            "Visibility": "Collapsed"
                        },
                        {
                            "XamlType": "Windows.UI.Xaml.Controls.Border",
                            "Background": "#FFE6E6E6",
                            "BorderBrush": "null",
                            "BorderThickness": "0,0,0,0",
                            "Clip": "null",
                            "CornerRadius": "0,0,0,0",
                            "FlowDirection": "LeftToRight",
                            "HorizontalAlignment": "Stretch",
                            "Margin": "0,0,0,0",
                            "Name": "ScrollBarSeparator",
                            "Padding": "0,0,0,0",
                            "RenderSize": "0,0",
                            "VerticalAlignment": "Stretch",
                            "Visibility": "Collapsed"
                        }
                        ]
                    }
                    ]
                }
                ]
            },
            {
                "XamlType": "Windows.UI.Xaml.Controls.TextBlock",
                "Clip": "null",
                "FlowDirection": "LeftToRight",
                "Foreground": "#B3E1E1E1",
                "HorizontalAlignment": "Stretch",
                "Margin": "1,1,1,1",
                "Name": "PlaceholderTextContentPresenter",
                "Padding": "10,10,10,10",
                "RenderSize": "798.2857,48",
                "VerticalAlignment": "Stretch",
                "Visibility": "Visible"
            },
            {
                "XamlType": "Windows.UI.Xaml.Controls.Button",
                "Background": "#33000000",
                "BorderBrush": "#00FFFFFF",
                "BorderThickness": "1,1,1,1",
                "Clip": "null",
                "CornerRadius": "0,0,0,0",
                "FlowDirection": "LeftToRight",
                "Foreground": "#FF000000",
                "HorizontalAlignment": "Left",
                "Margin": "0,0,0,0",
                "Name": "DeleteButton",
                "Padding": "0,0,-2,0",
                "RenderSize": "0,0",
                "VerticalAlignment": "Stretch",
                "Visibility": "Collapsed"
            },
            {
                "XamlType": "Windows.UI.Xaml.Controls.ContentPresenter",
                "Background": "null",
                "BorderBrush": "null",
                "BorderThickness": "0,0,0,0",
                "Clip": "null",
                "CornerRadius": "0,0,0,0",
                "FlowDirection": "LeftToRight",
                "Foreground": "#99000000",
                "HorizontalAlignment": "Stretch",
                "Margin": "0,0,0,0",
                "Name": "DescriptionPresenter",
                "Padding": "0,0,0,0",
                "RenderSize": "800,0",
                "VerticalAlignment": "Stretch",
                "Visibility": "Visible"
            }
            ]
        }
        ]
    },
    {
        "XamlType": "Windows.UI.Xaml.Controls.PasswordBox",
        "Background": "#33E1E1E1",
        "BorderBrush": "#55FF00FF",
        "BorderThickness": "1,1,1,1",
        "Clip": "null",
        "CornerRadius": "0,0,0,0",
        "FlowDirection": "LeftToRight",
        "Foreground": "#FFFFFFFF",
        "Height": "50",
        "HorizontalAlignment": "Stretch",
        "Margin": "0,0,0,0",
        "Padding": "10,10,10,10",
        "RenderSize": "800,50.28571",
        "VerticalAlignment": "Stretch",
        "Visibility": "Visible",
        "Width": "800",
        "children": [
        {
            "XamlType": "Windows.UI.Xaml.Controls.Grid",
            "Background": "null",
            "BorderBrush": "null",
            "BorderThickness": "0,0,0,0",
            "Clip": "null",
            "CornerRadius": "0,0,0,0",
            "FlowDirection": "LeftToRight",
            "HorizontalAlignment": "Stretch",
            "Margin": "0,0,0,0",
            "Padding": "0,0,0,0",
            "RenderSize": "800,50.28571",
            "VerticalAlignment": "Stretch",
            "Visibility": "Visible",
            "children": [
            {
                "XamlType": "Windows.UI.Xaml.Controls.Border",
                "Background": "#33E1E1E1",
                "BorderBrush": "#55FF00FF",
                "BorderThickness": "1,1,1,1",
                "Clip": "null",
                "CornerRadius": "0,0,0,0",
                "FlowDirection": "LeftToRight",
                "HorizontalAlignment": "Stretch",
                "Margin": "0,0,0,0",
                "Name": "BorderElement",
                "Padding": "0,0,0,0",
                "RenderSize": "800,50.28571",
                "VerticalAlignment": "Stretch",
                "Visibility": "Visible"
            },
            {
                "XamlType": "Windows.UI.Xaml.Controls.ScrollViewer",
                "Background": "#00FFFFFF",
                "BorderBrush": "#00FFFFFF",
                "BorderThickness": "0,0,0,0",
                "Clip": "null",
                "CornerRadius": "0,0,0,0",
                "FlowDirection": "LeftToRight",
                "Foreground": "#FFFFFFFF",
                "HorizontalAlignment": "Stretch",
                "Margin": "1,1,1,1",
                "Name": "ContentElement",
                "Padding": "10,10,10,10",
                "RenderSize": "798.2857,48",
                "VerticalAlignment": "Stretch",
                "Visibility": "Visible",
                "children": [
                {
                    "XamlType": "Windows.UI.Xaml.Controls.Border",
                    "Background": "null",
                    "BorderBrush": "#00FFFFFF",
                    "BorderThickness": "0,0,0,0",
                    "Clip": "null",
                    "CornerRadius": "0,0,0,0",
                    "FlowDirection": "LeftToRight",
                    "HorizontalAlignment": "Stretch",
                    "Margin": "0,0,0,0",
                    "Name": "Root",
                    "Padding": "0,0,0,0",
                    "RenderSize": "798.2857,48",
                    "VerticalAlignment": "Stretch",
                    "Visibility": "Visible",
                    "children": [
                    {
                        "XamlType": "Windows.UI.Xaml.Controls.Grid",
                        "Background": "#00FFFFFF",
                        "BorderBrush": "null",
                        "BorderThickness": "0,0,0,0",
                        "Clip": "null",
                        "CornerRadius": "0,0,0,0",
                        "FlowDirection": "LeftToRight",
                        "HorizontalAlignment": "Stretch",
                        "Margin": "0,0,0,0",
                        "Padding": "0,0,0,0",
                        "RenderSize": "798.2857,48",
                        "VerticalAlignment": "Stretch",
                        "Visibility": "Visible",
                        "children": [
                        {
                            "XamlType": "Windows.UI.Xaml.Controls.ScrollContentPresenter",
                            "Background": "null",
                            "BorderBrush": "null",
                            "BorderThickness": "0,0,0,0",
                            "Clip": "Windows.UI.Xaml.Media.RectangleGeometry",
                            "CornerRadius": "0,0,0,0",
                            "FlowDirection": "LeftToRight",
                            "Foreground": "#FFFFFFFF",
                            "HorizontalAlignment": "Stretch",
                            "Margin": "10,10,10,10",
                            "Name": "ScrollContentPresenter",
                            "Padding": "0,0,0,0",
                            "RenderSize": "778.2857,28",
                            "VerticalAlignment": "Stretch",
                            "Visibility": "Visible",
                            "children": [
                            {
                                "XamlType": "Windows.UI.Xaml.FrameworkElement",
                                "Clip": "null",
                                "FlowDirection": "LeftToRight",
                                "HorizontalAlignment": "Stretch",
                                "Margin": "0,0,0,0",
                                "RenderSize": "778.2857,28",
                                "VerticalAlignment": "Stretch",
                                "Visibility": "Visible"
                            }
                            ]
                        },
                        {
                            "XamlType": "Windows.UI.Xaml.Controls.Grid",
                            "Background": "null",
                            "BorderBrush": "null",
                            "BorderThickness": "0,0,0,0",
                            "Clip": "null",
                            "CornerRadius": "0,0,0,0",
                            "FlowDirection": "LeftToRight",
                            "HorizontalAlignment": "Stretch",
                            "Margin": "0,0,0,0",
                            "Padding": "0,0,0,0",
                            "RenderSize": "798.2857,48",
                            "VerticalAlignment": "Stretch",
                            "Visibility": "Visible"
                        },
                        {
                            "XamlType": "Windows.UI.Xaml.Controls.Primitives.ScrollBar",
                            "Background": "#00FFFFFF",
                            "BorderBrush": "#00FFFFFF",
                            "BorderThickness": "0,0,0,0",
                            "Clip": "null",
                            "CornerRadius": "2,2,2,2",
                            "FlowDirection": "LeftToRight",
                            "Foreground": "#00FFFFFF",
                            "HorizontalAlignment": "Right",
                            "Margin": "0,0,0,0",
                            "Name": "VerticalScrollBar",
                            "Padding": "0,0,0,0",
                            "RenderSize": "0,0",
                            "VerticalAlignment": "Stretch",
                            "Visibility": "Collapsed"
                        },
                        {
                            "XamlType": "Windows.UI.Xaml.Controls.Primitives.ScrollBar",
                            "Background": "#00FFFFFF",
                            "BorderBrush": "#00FFFFFF",
                            "BorderThickness": "0,0,0,0",
                            "Clip": "null",
                            "CornerRadius": "2,2,2,2",
                            "FlowDirection": "LeftToRight",
                            "Foreground": "#00FFFFFF",
                            "HorizontalAlignment": "Stretch",
                            "Margin": "0,0,0,0",
                            "Name": "HorizontalScrollBar",
                            "Padding": "0,0,0,0",
                            "RenderSize": "0,0",
                            "VerticalAlignment": "Stretch",
                            "Visibility": "Collapsed"
                        },
                        {
                            "XamlType": "Windows.UI.Xaml.Controls.Border",
                            "Background": "#FFE6E6E6",
                            "BorderBrush": "null",
                            "BorderThickness": "0,0,0,0",
                            "Clip": "null",
                            "CornerRadius": "0,0,0,0",
                            "FlowDirection": "LeftToRight",
                            "HorizontalAlignment": "Stretch",
                            "Margin": "0,0,0,0",
                            "Name": "ScrollBarSeparator",
                            "Padding": "0,0,0,0",
                            "RenderSize": "0,0",
                            "VerticalAlignment": "Stretch",
                            "Visibility": "Collapsed"
                        }
                        ]
                    }
                    ]
                }
                ]
            },
            {
                "XamlType": "Windows.UI.Xaml.Controls.TextBlock",
                "Clip": "null",
                "FlowDirection": "LeftToRight",
                "Foreground": "#B3E1E1E1",
                "HorizontalAlignment": "Stretch",
                "Margin": "1,1,1,1",
                "Name": "PlaceholderTextContentPresenter",
                "Padding": "10,10,10,10",
                "RenderSize": "798.2857,48",
                "VerticalAlignment": "Stretch",
                "Visibility": "Visible"
            },
            {
                "XamlType": "Windows.UI.Xaml.Controls.Primitives.ToggleButton",
                "Background": "#33000000",
                "BorderBrush": "#00FFFFFF",
                "BorderThickness": "1,1,1,1",
                "Clip": "null",
                "CornerRadius": "0,0,0,0",
                "FlowDirection": "LeftToRight",
                "Foreground": "#FF000000",
                "HorizontalAlignment": "Left",
                "Margin": "0,0,0,0",
                "Name": "RevealButton",
                "Padding": "0,0,-2,0",
                "RenderSize": "0,0",
                "VerticalAlignment": "Stretch",
                "Visibility": "Collapsed"
            },
            {
                "XamlType": "Windows.UI.Xaml.Controls.ContentPresenter",
                "Background": "null",
                "BorderBrush": "null",
                "BorderThickness": "0,0,0,0",
                "Clip": "null",
                "CornerRadius": "0,0,0,0",
                "FlowDirection": "LeftToRight",
                "Foreground": "#99000000",
                "HorizontalAlignment": "Stretch",
                "Margin": "0,0,0,0",
                "Name": "DescriptionPresenter",
                "Padding": "0,0,0,0",
                "RenderSize": "800,0",
                "VerticalAlignment": "Stretch",
                "Visibility": "Visible"
            }
            ]
        }
        ]
    },
    {
        "XamlType": "Windows.UI.Xaml.Controls.CalendarDatePicker",
        "Background": "#33E1E1E1",
        "BorderBrush": "#55FF00FF",
        "BorderThickness": "1,1,1,1",
        "Clip": "null",
        "CornerRadius": "0,0,0,0",
        "FlowDirection": "LeftToRight",
        "Foreground": "#FFFFFFFF",
        "Height": "50",
        "HorizontalAlignment": "Left",
        "Margin": "0,0,0,0",
        "Padding": "0,0,0,0",
        "RenderSize": "150.2857,50.28571",
        "VerticalAlignment": "Center",
        "Visibility": "Visible",
        "Width": "150",
        "children": [
        {
            "XamlType": "Windows.UI.Xaml.Controls.Grid",
            "Background": "null",
            "BorderBrush": "null",
            "BorderThickness": "0,0,0,0",
            "Clip": "null",
            "CornerRadius": "0,0,0,0",
            "FlowDirection": "LeftToRight",
            "HorizontalAlignment": "Stretch",
            "Margin": "0,0,0,0",
            "Name": "Root",
            "Padding": "0,0,0,0",
            "RenderSize": "150.2857,50.28571",
            "VerticalAlignment": "Stretch",
            "Visibility": "Visible",
            "children": [
            {
                "XamlType": "Windows.UI.Xaml.Controls.Border",
                "Background": "#33E1E1E1",
                "BorderBrush": "#55FF00FF",
                "BorderThickness": "1,1,1,1",
                "Clip": "null",
                "CornerRadius": "0,0,0,0",
                "FlowDirection": "LeftToRight",
                "HorizontalAlignment": "Stretch",
                "Margin": "0,0,0,0",
                "Name": "Background",
                "Padding": "0,0,0,0",
                "RenderSize": "150.2857,50.28571",
                "VerticalAlignment": "Stretch",
                "Visibility": "Visible"
            },
            {
                "XamlType": "Windows.UI.Xaml.Controls.TextBlock",
                "Clip": "null",
                "FlowDirection": "LeftToRight",
                "Foreground": "#99000000",
                "HorizontalAlignment": "Left",
                "Margin": "0,0,0,0",
                "Name": "DateText",
                "Padding": "12,0,0,2",
                "RenderSize": "104.5714,24.57143",
                "VerticalAlignment": "Center",
                "Visibility": "Visible"
            },
            {
                "XamlType": "Windows.UI.Xaml.Controls.FontIcon",
                "Clip": "null",
                "FlowDirection": "LeftToRight",
                "Foreground": "#CC000000",
                "HorizontalAlignment": "Center",
                "Margin": "0,0,0,0",
                "Name": "CalendarGlyph",
                "RenderSize": "12,12",
                "VerticalAlignment": "Center",
                "Visibility": "Visible",
                "children": [
                {
                    "XamlType": "Windows.UI.Xaml.Controls.Grid",
                    "Background": "#00000000",
                    "BorderBrush": "null",
                    "BorderThickness": "0,0,0,0",
                    "Clip": "null",
                    "CornerRadius": "0,0,0,0",
                    "FlowDirection": "LeftToRight",
                    "HorizontalAlignment": "Stretch",
                    "Margin": "0,0,0,0",
                    "Padding": "0,0,0,0",
                    "RenderSize": "12,12",
                    "VerticalAlignment": "Stretch",
                    "Visibility": "Visible",
                    "children": [
                    {
                        "XamlType": "Windows.UI.Xaml.Controls.TextBlock",
                        "Clip": "null",
                        "FlowDirection": "LeftToRight",
                        "Foreground": "#CC000000",
                        "HorizontalAlignment": "Stretch",
                        "Margin": "0,0,0,0",
                        "Padding": "0,0,0,0",
                        "RenderSize": "12,12",
                        "VerticalAlignment": "Center",
                        "Visibility": "Visible"
                    }
                    ]
                }
                ]
            },
            {
                "XamlType": "Windows.UI.Xaml.Controls.ContentPresenter",
                "Background": "null",
                "BorderBrush": "null",
                "BorderThickness": "0,0,0,0",
                "Clip": "null",
                "CornerRadius": "0,0,0,0",
                "FlowDirection": "LeftToRight",
                "Foreground": "#99000000",
                "HorizontalAlignment": "Stretch",
                "Margin": "0,0,0,0",
                "Name": "DescriptionPresenter",
                "Padding": "0,0,0,0",
                "RenderSize": "150.2857,0",
                "VerticalAlignment": "Stretch",
                "Visibility": "Visible"
            }
            ]
        }
        ]
    },
    {
        "XamlType": "Windows.UI.Xaml.Controls.ComboBox",
        "Background": "#33E1E1E1",
        "BorderBrush": "#55FF00FF",
        "BorderThickness": "1,1,1,1",
        "Clip": "null",
        "CornerRadius": "0,0,0,0",
        "FlowDirection": "LeftToRight",
        "Foreground": "#FFFFFFFF",
        "Height": "50",
        "HorizontalAlignment": "Left",
        "Margin": "0,0,0,0",
        "Padding": "12,5,0,7",
        "RenderSize": "800,50.28571",
        "VerticalAlignment": "Top",
        "Visibility": "Visible",
        "Width": "800",
        "children": [
        {
            "XamlType": "Windows.UI.Xaml.Controls.Grid",
            "Background": "null",
            "BorderBrush": "null",
            "BorderThickness": "0,0,0,0",
            "Clip": "null",
            "CornerRadius": "0,0,0,0",
            "FlowDirection": "LeftToRight",
            "HorizontalAlignment": "Stretch",
            "Margin": "0,0,0,0",
            "Name": "LayoutRoot",
            "Padding": "0,0,0,0",
            "RenderSize": "800,50.28571",
            "VerticalAlignment": "Stretch",
            "Visibility": "Visible",
            "children": [
            {
                "XamlType": "Windows.UI.Xaml.Controls.Border",
                "Background": "#33E1E1E1",
                "BorderBrush": "#55FF00FF",
                "BorderThickness": "1,1,1,1",
                "Clip": "null",
                "CornerRadius": "0,0,0,0",
                "FlowDirection": "LeftToRight",
                "HorizontalAlignment": "Stretch",
                "Margin": "0,0,0,0",
                "Name": "Background",
                "Padding": "0,0,0,0",
                "RenderSize": "800,50.28571",
                "VerticalAlignment": "Stretch",
                "Visibility": "Visible"
            },
            {
                "XamlType": "Windows.UI.Xaml.Controls.Border",
                "Background": "#FF409EFE",
                "BorderBrush": "#66000000",
                "BorderThickness": "1,1,1,1",
                "Clip": "null",
                "CornerRadius": "0,0,0,0",
                "FlowDirection": "LeftToRight",
                "HorizontalAlignment": "Stretch",
                "Margin": "0,0,0,0",
                "Name": "HighlightBackground",
                "Padding": "0,0,0,0",
                "RenderSize": "800,50.28571",
                "VerticalAlignment": "Stretch",
                "Visibility": "Visible"
            },
            {
                "XamlType": "Windows.UI.Xaml.Controls.ContentPresenter",
                "Background": "null",
                "BorderBrush": "null",
                "BorderThickness": "0,0,0,0",
                "Clip": "null",
                "CornerRadius": "0,0,0,0",
                "FlowDirection": "LeftToRight",
                "Foreground": "#FFFFFFFF",
                "HorizontalAlignment": "Stretch",
                "Margin": "12,5,0,7",
                "Name": "ContentPresenter",
                "Padding": "0,0,0,0",
                "RenderSize": "756,22.28572",
                "VerticalAlignment": "Center",
                "Visibility": "Visible",
                "children": [
                {
                    "XamlType": "Windows.UI.Xaml.Controls.TextBlock",
                    "Clip": "null",
                    "FlowDirection": "LeftToRight",
                    "Foreground": "#FF000000",
                    "HorizontalAlignment": "Stretch",
                    "Margin": "0,0,0,0",
                    "Name": "PlaceholderTextBlock",
                    "Padding": "0,0,0,0",
                    "RenderSize": "756,22.28572",
                    "VerticalAlignment": "Stretch",
                    "Visibility": "Visible"
                }
                ]
            },
            {
                "XamlType": "Windows.UI.Xaml.Controls.TextBox",
                "Background": "#66FFFFFF",
                "BorderBrush": "#00FFFFFF",
                "BorderThickness": "1,1,1,1",
                "Clip": "null",
                "CornerRadius": "0,0,0,0",
                "FlowDirection": "LeftToRight",
                "Foreground": "#FF000000",
                "HorizontalAlignment": "Stretch",
                "Margin": "0,0,0,0",
                "Name": "EditableText",
                "Padding": "11,5,32,6",
                "RenderSize": "0,0",
                "VerticalAlignment": "Center",
                "Visibility": "Collapsed"
            },
            {
                "XamlType": "Windows.UI.Xaml.Controls.Border",
                "Background": "#00FFFFFF",
                "BorderBrush": "null",
                "BorderThickness": "0,0,0,0",
                "Clip": "null",
                "CornerRadius": "0,0,0,0",
                "FlowDirection": "LeftToRight",
                "HorizontalAlignment": "Right",
                "Margin": "0,1,1,1",
                "Name": "DropDownOverlay",
                "Padding": "0,0,0,0",
                "RenderSize": "0,0",
                "VerticalAlignment": "Stretch",
                "Visibility": "Collapsed",
                "Width": "30"
            },
            {
                "XamlType": "Windows.UI.Xaml.Controls.FontIcon",
                "Clip": "null",
                "FlowDirection": "LeftToRight",
                "Foreground": "#CC000000",
                "HorizontalAlignment": "Right",
                "Margin": "0,0,10,0",
                "Name": "DropDownGlyph",
                "RenderSize": "12,32",
                "VerticalAlignment": "Center",
                "Visibility": "Visible",
                "children": [
                {
                    "XamlType": "Windows.UI.Xaml.Controls.Grid",
                    "Background": "#00000000",
                    "BorderBrush": "null",
                    "BorderThickness": "0,0,0,0",
                    "Clip": "null",
                    "CornerRadius": "0,0,0,0",
                    "FlowDirection": "LeftToRight",
                    "HorizontalAlignment": "Stretch",
                    "Margin": "0,0,0,0",
                    "Padding": "0,0,0,0",
                    "RenderSize": "12,32",
                    "VerticalAlignment": "Stretch",
                    "Visibility": "Visible",
                    "children": [
                    {
                        "XamlType": "Windows.UI.Xaml.Controls.TextBlock",
                        "Clip": "null",
                        "FlowDirection": "LeftToRight",
                        "Foreground": "#CC000000",
                        "HorizontalAlignment": "Stretch",
                        "Margin": "0,0,0,0",
                        "Padding": "0,0,0,0",
                        "RenderSize": "12,12",
                        "VerticalAlignment": "Center",
                        "Visibility": "Visible"
                    }
                    ]
                }
                ]
            },
            {
                "XamlType": "Windows.UI.Xaml.Controls.ContentPresenter",
                "Background": "null",
                "BorderBrush": "null",
                "BorderThickness": "0,0,0,0",
                "Clip": "null",
                "CornerRadius": "0,0,0,0",
                "FlowDirection": "LeftToRight",
                "Foreground": "#99000000",
                "HorizontalAlignment": "Stretch",
                "Margin": "0,0,0,0",
                "Name": "DescriptionPresenter",
                "Padding": "0,0,0,0",
                "RenderSize": "800,0",
                "VerticalAlignment": "Stretch",
                "Visibility": "Visible"
            },
            {
                "XamlType": "Windows.UI.Xaml.Controls.Primitives.Popup",
                "Clip": "null",
                "FlowDirection": "LeftToRight",
                "HorizontalAlignment": "Stretch",
                "Margin": "0,0,0,0",
                "Name": "Popup",
                "RenderSize": "768,0",
                "VerticalAlignment": "Stretch",
                "Visibility": "Visible"
            }
            ]
        }
        ]
    }
    ]
}
